infratools/__init__.py
infratools/aws.py
infratools/rabbitmq.py
infratools/slack.py
tests/__init__.py
infratools-0.1.0.dist-info/LICENSE
infratools-0.1.0.dist-info/METADATA
infratools-0.1.0.dist-info/WHEEL
infratools-0.1.0.dist-info/top_level.txt
infratools-0.1.0.dist-info/RECORD
